README.md
setup.py
examples/__init__.py
examples/async_basic_talk.py
examples/async_custom_talk.py
examples/base_talk.py
examples/knowledge_warehouse.py
examples/origin.py
examples/personalized_talk.py
examples/satisfaction_collection.py
logs/__init__.py
tests/__init__.py
tests/test_client.py
tests/test_client_config.py
tests/test_client_dictionary.py
tests/test_client_knowledge.py
tests/test_client_nlp.py
tests/test_client_stats.py
tests/test_client_talk.py
tests/test_client_task.py
tests/test_client_user.py
tests/test_request.py
wulaisdk/__init__.py
wulaisdk/client.py
wulaisdk/exceptions.py
wulaisdk/http.py
wulaisdk/http_codes.py
wulaisdk/request.py
wulaisdk.egg-info/PKG-INFO
wulaisdk.egg-info/SOURCES.txt
wulaisdk.egg-info/dependency_links.txt
wulaisdk.egg-info/requires.txt
wulaisdk.egg-info/top_level.txt
wulaisdk/response/__init__.py
wulaisdk/response/bot.py
wulaisdk/response/category_config.py
wulaisdk/response/category_dictionary.py
wulaisdk/response/category_knowledge.py
wulaisdk/response/category_nlp.py
wulaisdk/response/category_stats.py
wulaisdk/response/category_talk.py
wulaisdk/response/category_task.py
wulaisdk/response/category_user.py
wulaisdk/response/msg_body.py