Metadata-Version: 1.0
Name: wulaisdk
Version: 1.1.8
Summary: Laiye Wulai SDK for Python Programming Language
Home-page: https://github.com/laiye-ai/wulai-openapi-sdk-python
Author: shierlou
Author-email: manbugv@gmail.com
License: LICENSE Apache 2.0
Platform: any
